{
  "properties": [
    {
      "name": "lenjoy.security.tokenHeader",
      "type": "java.lang.String",
      "description": "Description for lenjoy.security.tokenHeader."
    },
    {
      "name": "lenjoy.security.tokenHeaderPrefix",
      "type": "java.lang.String",
      "description": "Description for lenjoy.security.tokenHeaderPrefix."
    },
    {
      "name": "lenjoy.security.tokenTimeout",
      "type": "java.lang.String",
      "description": "Description for lenjoy.security.tokenTimeout."
    },
    {
      "name": "lenjoy.security.sessionTimeout",
      "type": "java.lang.String",
      "description": "Description for lenjoy.security.sessionTimeout."
    }
  ]
}